scrape_sanskrit/__init__.py
scrape_sanskrit/scraper.py
scraper_sanskrit-0.2.0.dist-info/METADATA
scraper_sanskrit-0.2.0.dist-info/WHEEL
scraper_sanskrit-0.2.0.dist-info/top_level.txt
scraper_sanskrit-0.2.0.dist-info/RECORD
