Metadata-Version: 2.1
Name: scraper-sanskrit
Version: 0.2.0
Summary: A web scraper for Sanskrit dictionary results using Selenium and BeautifulSoup
Author: Jagruti
License: MIT
Classifier: Programming Language :: Python :: 3
Classifier: License :: OSI Approved :: MIT License
Classifier: Operating System :: OS Independent
Requires-Python: >=3.6
Requires-Dist: selenium
Requires-Dist: webdriver-manager
Requires-Dist: beautifulsoup4
